
// Copyright 2015 Google Inc. All Rights Reserved.
//
// Licensed under the Apache License, Version 2.0 (the "License");
// you may not use this file except in compliance with the License.
// You may obtain a copy of the License at
//
//     http://www.apache.org/licenses/LICENSE-2.0
//
// Unless required by applicable law or agreed to in writing, software
// distributed under the License is distributed on an "AS IS" BASIS,
// WITHOUT WARRANTIES OR CONDITIONS OF ANY KIND, either express or implied.
// See the License for the specific language governing permissions and
// limitations under the License.

// Autogenerated by genjvmops.py - do not edit

package constants

const NOP = 0x00
const ACONST_NULL = 0x01
const ICONST_M1 = 0x02
const ICONST_0 = 0x03
const ICONST_1 = 0x04
const ICONST_2 = 0x05
const ICONST_3 = 0x06
const ICONST_4 = 0x07
const ICONST_5 = 0x08
const LCONST_0 = 0x09
const LCONST_1 = 0x0A
const FCONST_0 = 0x0B
const FCONST_1 = 0x0C
const FCONST_2 = 0x0D
const DCONST_0 = 0x0E
const DCONST_1 = 0x0F
const BIPUSH = 0x10
const SIPUSH = 0x11
const LDC = 0x12
const LDC_W = 0x13
const LDC2_W = 0x14
const ILOAD = 0x15
const LLOAD = 0x16
const FLOAD = 0x17
const DLOAD = 0x18
const ALOAD = 0x19
const ILOAD_0 = 0x1A
const ILOAD_1 = 0x1B
const ILOAD_2 = 0x1C
const ILOAD_3 = 0x1D
const LLOAD_0 = 0x1E
const LLOAD_1 = 0x1F
const LLOAD_2 = 0x20
const LLOAD_3 = 0x21
const FLOAD_0 = 0x22
const FLOAD_1 = 0x23
const FLOAD_2 = 0x24
const FLOAD_3 = 0x25
const DLOAD_0 = 0x26
const DLOAD_1 = 0x27
const DLOAD_2 = 0x28
const DLOAD_3 = 0x29
const ALOAD_0 = 0x2A
const ALOAD_1 = 0x2B
const ALOAD_2 = 0x2C
const ALOAD_3 = 0x2D
const IALOAD = 0x2E
const LALOAD = 0x2F
const FALOAD = 0x30
const DALOAD = 0x31
const AALOAD = 0x32
const BALOAD = 0x33
const CALOAD = 0x34
const SALOAD = 0x35
const ISTORE = 0x36
const LSTORE = 0x37
const FSTORE = 0x38
const DSTORE = 0x39
const ASTORE = 0x3A
const ISTORE_0 = 0x3B
const ISTORE_1 = 0x3C
const ISTORE_2 = 0x3D
const ISTORE_3 = 0x3E
const LSTORE_0 = 0x3F
const LSTORE_1 = 0x40
const LSTORE_2 = 0x41
const LSTORE_3 = 0x42
const FSTORE_0 = 0x43
const FSTORE_1 = 0x44
const FSTORE_2 = 0x45
const FSTORE_3 = 0x46
const DSTORE_0 = 0x47
const DSTORE_1 = 0x48
const DSTORE_2 = 0x49
const DSTORE_3 = 0x4A
const ASTORE_0 = 0x4B
const ASTORE_1 = 0x4C
const ASTORE_2 = 0x4D
const ASTORE_3 = 0x4E
const IASTORE = 0x4F
const LASTORE = 0x50
const FASTORE = 0x51
const DASTORE = 0x52
const AASTORE = 0x53
const BASTORE = 0x54
const CASTORE = 0x55
const SASTORE = 0x56
const POP = 0x57
const POP2 = 0x58
const DUP = 0x59
const DUP_X1 = 0x5A
const DUP_X2 = 0x5B
const DUP2 = 0x5C
const DUP2_X1 = 0x5D
const DUP2_X2 = 0x5E
const SWAP = 0x5F
const IADD = 0x60
const LADD = 0x61
const FADD = 0x62
const DADD = 0x63
const ISUB = 0x64
const LSUB = 0x65
const FSUB = 0x66
const DSUB = 0x67
const IMUL = 0x68
const LMUL = 0x69
const FMUL = 0x6A
const DMUL = 0x6B
const IDIV = 0x6C
const LDIV = 0x6D
const FDIV = 0x6E
const DDIV = 0x6F
const IREM = 0x70
const LREM = 0x71
const FREM = 0x72
const DREM = 0x73
const INEG = 0x74
const LNEG = 0x75
const FNEG = 0x76
const DNEG = 0x77
const ISHL = 0x78
const LSHL = 0x79
const ISHR = 0x7A
const LSHR = 0x7B
const IUSHR = 0x7C
const LUSHR = 0x7D
const IAND = 0x7E
const LAND = 0x7F
const IOR = 0x80
const LOR = 0x81
const IXOR = 0x82
const LXOR = 0x83
const IINC = 0x84
const I2L = 0x85
const I2F = 0x86
const I2D = 0x87
const L2I = 0x88
const L2F = 0x89
const L2D = 0x8A
const F2I = 0x8B
const F2L = 0x8C
const F2D = 0x8D
const D2I = 0x8E
const D2L = 0x8F
const D2F = 0x90
const I2B = 0x91
const I2C = 0x92
const I2S = 0x93
const LCMP = 0x94
const FCMPL = 0x95
const FCMPG = 0x96
const DCMPL = 0x97
const DCMPG = 0x98
const IFEQ = 0x99
const IFNE = 0x9A
const IFLT = 0x9B
const IFGE = 0x9C
const IFGT = 0x9D
const IFLE = 0x9E
const IF_ICMPEQ = 0x9F
const IF_ICMPNE = 0xA0
const IF_ICMPLT = 0xA1
const IF_ICMPGE = 0xA2
const IF_ICMPGT = 0xA3
const IF_ICMPLE = 0xA4
const IF_ACMPEQ = 0xA5
const IF_ACMPNE = 0xA6
const GOTO = 0xA7
const JSR = 0xA8
const RET = 0xA9
const TABLESWITCH = 0xAA
const LOOKUPSWITCH = 0xAB
const IRETURN = 0xAC
const LRETURN = 0xAD
const FRETURN = 0xAE
const DRETURN = 0xAF
const ARETURN = 0xB0
const RETURN = 0xB1
const GETSTATIC = 0xB2
const PUTSTATIC = 0xB3
const GETFIELD = 0xB4
const PUTFIELD = 0xB5
const INVOKEVIRTUAL = 0xB6
const INVOKESPECIAL = 0xB7
const INVOKESTATIC = 0xB8
const INVOKEINTERFACE = 0xB9
const INVOKEDYNAMIC = 0xBA
const NEW = 0xBB
const NEWARRAY = 0xBC
const ANEWARRAY = 0xBD
const ARRAYLENGTH = 0xBE
const ATHROW = 0xBF
const CHECKCAST = 0xC0
const INSTANCEOF = 0xC1
const MONITORENTER = 0xC2
const MONITOREXIT = 0xC3
const WIDE = 0xC4
const MULTIANEWARRAY = 0xC5
const IFNULL = 0xC6
const IFNONNULL = 0xC7
const GOTO_W = 0xC8
const JSR_W = 0xC9
